[
    {
        "Name": "Business Partner"
    },
    {
        "Name": "Study Group"
    },
    {
        "Name": "Exercise Buddy"
    },
    {
        "Name": "Art Collaboration"
    },
    {
        "Name": "Travel Companion"
    },
    {
        "Name": "Music Band"
    },
    {
        "Name": "Book Club"
    },
    {
        "Name": "Dance Partner"
    },
    {
        "Name": "Language Exchange"
    },
    {
        "Name": "Gaming Squad"
    },
    {
        "Name": "Photography Project"
    },
    {
        "Name": "Coding Team"
    },
    {
        "Name": "Start-up Co-founder"
    },
    {
        "Name": "Investment Group"
    },
    {
        "Name": "Motivation Partners"
    },
    {
        "Name": "Film Making Collaboration"
    },
    {
        "Name": "Poetry Reading"
    },
    {
        "Name": "Stand-up Comedy"
    },
    {
        "Name": "Philosophy Discussion"
    },
    {
        "Name": "Astronomy Enthusiasts"
    },
    {
        "Name": "Dog Walking"
    },
    {
        "Name": "Fashion Advice"
    },
    {
        "Name": "Crafting Tips"
    },
    {
        "Name": "Car Repair Advice"
    },
    {
        "Name": "Environmental Conservation"
    },
    {
        "Name": "Cooking Classes"
    },
    {
        "Name": "Financial Planning"
    },
    {
        "Name": "Graphic Design Tips"
    },
    {
        "Name": "Real Estate Advice"
    },
    {
        "Name": "Gardening Club"
    },
    {
        "Name": "Board Game Partners"
    },
    {
        "Name": "Music Festival Buddies"
    },
    {
        "Name": "Sports Training"
    },
    {
        "Name": "Travel Photography"
    },
    {
        "Name": "Career Guidance"
    },
    {
        "Name": "Wellness Tips"
    },
    {
        "Name": "Academic Research"
    },
    {
        "Name": "Mental Health Support"
    },
    {
        "Name": "Nutrition Advice"
    },
    {
        "Name": "Entrepreneurship Ideas"
    },
    {
        "Name": "Film Discussion"
    },
    {
        "Name": "Writing Workshop"
    },
    {
        "Name": "Drawing Lessons"
    },
    {
        "Name": "Book Writing"
    },
    {
        "Name": "Basketball Team"
    },
    {
        "Name": "Book Editing Help"
    },
    {
        "Name": "Chess Partner"
    },
    {
        "Name": "Drama Club"
    },
    {
        "Name": "Eco-friendly Initiatives"
    },
    {
        "Name": "Farming Advice"
    },
    {
        "Name": "Graphic Novel Discussion"
    },
    {
        "Name": "Heritage Conservation"
    },
    {
        "Name": "Interior Design Tips"
    },
    {
        "Name": "Jazz Ensemble"
    },
    {
        "Name": "Knitting Group"
    },
    {
        "Name": "Live Music Fans"
    },
    {
        "Name": "Mountain Climbing"
    },
    {
        "Name": "Non-profit Work"
    },
    {
        "Name": "Organic Gardening"
    },
    {
        "Name": "Poetry Writing"
    },
    {
        "Name": "Quiz Team"
    },
    {
        "Name": "Running Partners"
    },
    {
        "Name": "Sustainable Living"
    },
    {
        "Name": "Travel Vlog Collaboration"
    },
    {
        "Name": "Vintage Car Restoration"
    },
    {
        "Name": "Wildlife Photography"
    },
    {
        "Name": "Xbox Gaming"
    },
    {
        "Name": "Yacht Sailing"
    },
    {
        "Name": "Zumba Class"
    },
    {
        "Name": "Cookbook Club"
    },
    {
        "Name": "Digital Art Collaboration"
    },
    {
        "Name": "Exploration Hiking"
    },
    {
        "Name": "Film Production"
    },
    {
        "Name": "Social Justice Advocacy"
    },
    {
        "Name": "Virtual Reality Gaming"
    },
    {
        "Name": "STEM Tutoring"
    },
    {
        "Name": "Artificial Intelligence Discussion"
    },
    {
        "Name": "Web Development Help"
    },
    {
        "Name": "Theatre Enthusiasts"
    },
    {
        "Name": "Anime Club"
    },
    {
        "Name": "Biohacking Advice"
    },
    {
        "Name": "Cycling Group"
    },
    {
        "Name": "Data Science Project"
    },
    {
        "Name": "Ethical Fashion"
    },
    {
        "Name": "Food Critics"
    },
    {
        "Name": "Guitar Lessons"
    },
    {
        "Name": "Historical Research"
    },
    {
        "Name": "Investing Club"
    },
    {
        "Name": "Journalism Collaboration"
    },
    {
        "Name": "Knit and Natter"
    },
    {
        "Name": "Life Coaching"
    },
    {
        "Name": "Museum Tours"
    },
    {
        "Name": "Nature Walks"
    },
    {
        "Name": "Opera Fans"
    },
    {
        "Name": "Pottery Classes"
    },
    {
        "Name": "Quiz Nights"
    },
    {
        "Name": "Rooftop Gardening"
    },
    {
        "Name": "Scuba Diving"
    },
    {
        "Name": "Toastmasters Club"
    },
    {
        "Name": "Underwater Photography"
    },
    {
        "Name": "Vintage Clothing Swap"
    },
    {
        "Name": "Wildlife Conservation"
    },
    {
        "Name": "Xenobiology Discussion"
    },
    {
        "Name": "Yoga Retreats"
    },
    {
        "Name": "Zoology Research"
    },
    {
        "Name": "Acro Yoga"
    },
    {
        "Name": "Breakdance Battles"
    },
    {
        "Name": "Cryptocurrency Trading"
    },
    {
        "Name": "Drone Racing"
    },
    {
        "Name": "Esports Team"
    },
    {
        "Name": "Fencing Partners"
    },
    {
        "Name": "Geocaching Adventures"
    },
    {
        "Name": "Human Rights Advocacy"
    },
    {
        "Name": "Improv Comedy"
    },
    {
        "Name": "Jewellery Making"
    },
    {
        "Name": "Kayaking Trips"
    },
    {
        "Name": "Lindy Hop Dance"
    },
    {
        "Name": "Microbrewery Tours"
    },
    {
        "Name": "Night Photography"
    },
    {
        "Name": "Podcast Recording"
    },
    {
        "Name": "Quantum Physics Discussion"
    },
    {
        "Name": "Rock Climbing"
    },
    {
        "Name": "Salsa Dance Classes"
    },
    {
        "Name": "Tango Lessons"
    },
    {
        "Name": "Urban Sketching"
    },
    {
        "Name": "Vegan Cooking"
    },
    {
        "Name": "Wine Tasting"
    },
    {
        "Name": "Xbox Tournaments"
    },
    {
        "Name": "Yachting Club"
    },
    {
        "Name": "Zero Waste Initiatives"
    },
    {
        "Name": "Archaeology Excursions"
    },
    {
        "Name": "Beach Cleanups"
    },
    {
        "Name": "Crochet Classes"
    },
    {
        "Name": "Dungeons and Dragons Group"
    },
    {
        "Name": "Embroidery Lessons"
    },
    {
        "Name": "Foodie Tours"
    },
    {
        "Name": "Genealogy Research"
    },
    {
        "Name": "Historical Reenactment"
    },
    {
        "Name": "Italian Cooking"
    },
    {
        "Name": "Juggling Workshop"
    },
    {
        "Name": "Kiteboarding"
    },
    {
        "Name": "Lego Building"
    },
    {
        "Name": "Motorcycle Club"
    },
    {
        "Name": "Nordic Walking"
    },
    {
        "Name": "Orchestra Practice"
    },
    {
        "Name": "Poetry Slam"
    },
    {
        "Name": "Quilting Bee"
    },
    {
        "Name": "Robotics Club"
    },
    {
        "Name": "Stargazing Nights"
    },
    {
        "Name": "Tea Tasting"
    },
    {
        "Name": "Ukulele Lessons"
    },
    {
        "Name": "Virtual Choir"
    },
    {
        "Name": "Walking Tours"
    },
    {
        "Name": "Xeriscaping Techniques"
    },
    {
        "Name": "Youth Mentoring"
    },
    {
        "Name": "Zen Meditation"
    },
    {
        "Name": "DIY Project Help"
    },
    {
        "Name": "Crossfit Partners"
    },
    {
        "Name": "Aquarium Hobbyists"
    },
    {
        "Name": "Belly Dance Classes"
    },
    {
        "Name": "Creative Writing"
    },
    {
        "Name": "Drumming Lessons"
    },
    {
        "Name": "English Literature Discussion"
    },
    {
        "Name": "Flower Arranging"
    },
    {
        "Name": "Ghost Hunting"
    },
    {
        "Name": "Home Brewing"
    },
    {
        "Name": "Ice Skating Partners"
    },
    {
        "Name": "Japanese Calligraphy"
    },
    {
        "Name": "Kendo Practice"
    },
    {
        "Name": "Life Drawing Classes"
    },
    {
        "Name": "Murder Mystery Nights"
    },
    {
        "Name": "Numerology Discussion"
    },
    {
        "Name": "Organ Playing"
    },
    {
        "Name": "Puppetry Workshop"
    },
    {
        "Name": "Quidditch Team"
    },
    {
        "Name": "Renaissance Fairs"
    },
    {
        "Name": "Storytelling Evenings"
    },
    {
        "Name": "Tap Dance Lessons"
    },
    {
        "Name": "Urban Farming"
    },
    {
        "Name": "Vegetarian Cooking"
    },
    {
        "Name": "Whittling Group"
    },
    {
        "Name": "Xylophone Band"
    },
    {
        "Name": "Yoga Philosophy Discussion"
    },
    {
        "Name": "Zine Making"
    },
    {
        "Name": "Astrology Reading"
    },
    {
        "Name": "Bird Watching"
    },
    {
        "Name": "Cosplay Group"
    },
    {
        "Name": "Doll Making"
    },
    {
        "Name": "Equestrian Club"
    },
    {
        "Name": "Frisbee Golf"
    },
    {
        "Name": "Glassblowing Workshop"
    },
    {
        "Name": "Horror Film Club"
    },
    {
        "Name": "Indie Game Development"
    },
    {
        "Name": "Jigsaw Puzzle Club"
    },
    {
        "Name": "Kickboxing Class"
    },
    {
        "Name": "Latin Dance Classes"
    },
    {
        "Name": "Mime Workshop"
    },
    {
        "Name": "Numismatics Club"
    },
    {
        "Name": "Outdoor Adventure"
    },
    {
        "Name": "Plein Air Painting"
    },
    {
        "Name": "Quilting Club"
    },
    {
        "Name": "Reiki Healing"
    },
    {
        "Name": "Sculpture Workshop"
    },
    {
        "Name": "Tarot Reading"
    },
    {
        "Name": "Urban Foraging"
    },
    {
        "Name": "Vocal Training"
    },
    {
        "Name": "Wilderness Survival"
    },
    {
        "Name": "Xingyi Quan Practice"
    },
    {
        "Name": "Yo-yo Tricks"
    },
    {
        "Name": "Zen Buddhism Study"
    },
    {
        "Name": "Archery Club"
    },
    {
        "Name": "Baking Lessons"
    },
    {
        "Name": "Capoeira Practice"
    },
    {
        "Name": "Drone Photography"
    },
    {
        "Name": "Ethnomusicology Discussion"
    },
    {
        "Name": "Flamenco Dance Lessons"
    },
    {
        "Name": "Geology Field Trips"
    },
    {
        "Name": "Hiking Group"
    },
    {
        "Name": "Indoor Rock Climbing"
    },
    {
        "Name": "Jazz Dance Classes"
    },
    {
        "Name": "Kombucha Making"
    },
    {
        "Name": "Latin Language Study"
    },
    {
        "Name": "Metal Detecting"
    },
    {
        "Name": "Natural Soap Making"
    },
    {
        "Name": "Outdoor Photography"
    },
    {
        "Name": "Paintball Team"
    },
    {
        "Name": "Quantum Computing Discussion"
    },
    {
        "Name": "Roller Derby"
    },
    {
        "Name": "Social Impact Initiatives"
    },
    {
        "Name": "Tai Chi Practice"
    },
    {
        "Name": "Urban Hiking"
    },
    {
        "Name": "Vegan Baking"
    },
    {
        "Name": "Watercolor Painting"
    },
    {
        "Name": "Xiangqi (Chinese Chess) Partner"
    },
    {
        "Name": "Yacht Racing"
    },
    {
        "Name": "Zymurgy (Homebrewing Beer)"
    },
    {
        "Name": "Aquaponics Workshop"
    },
    {
        "Name": "Barista Training"
    },
    {
        "Name": "Classical Music Appreciation"
    },
    {
        "Name": "Dressmaking Club"
    },
    {
        "Name": "Esoteric Philosophy Discussion"
    },
    {
        "Name": "Film Noir Appreciation"
    },
    {
        "Name": "Graffiti Art Tour"
    },
    {
        "Name": "Hot Yoga Classes"
    },
    {
        "Name": "Indigenous Culture Study"
    },
    {
        "Name": "Jewelry Making Workshop"
    },
    {
        "Name": "Larping (Live Action Role Play)"
    },
    {
        "Name": "Mindfulness Meditation"
    },
    {
        "Name": "Nature Journaling"
    },
    {
        "Name": "Origami Club"
    },
    {
        "Name": "Potluck Dinners"
    },
    {
        "Name": "Qi Gong Practice"
    },
    {
        "Name": "Rugby Team"
    },
    {
        "Name": "Stand-up Paddleboarding"
    },
    {
        "Name": "Therapeutic Writing"
    },
    {
        "Name": "Upcycling Workshop"
    },
    {
        "Name": "Volunteer Opportunities"
    },
    {
        "Name": "Woodworking Class"
    },
    {
        "Name": "Xerophyte Gardening"
    },
    {
        "Name": "Yin Yoga Class"
    },
    {
        "Name": "Zero-waste Lifestyle"
    },
    {
        "Name": "Acoustic Guitar Jam"
    },
    {
        "Name": "Bird Photography"
    },
    {
        "Name": "Card Magic Tricks"
    },
    {
        "Name": "Dance Improvisation"
    },
    {
        "Name": "Endurance Training"
    },
    {
        "Name": "French Cooking"
    },
    {
        "Name": "Home Decor DIY"
    },
    {
        "Name": "Ice Sculpting"
    },
    {
        "Name": "Japanese Tea Ceremony"
    },
    {
        "Name": "Kick Scooter Riding"
    },
    {
        "Name": "Light Painting Photography"
    },
    {
        "Name": "Mystery Book Club"
    },
    {
        "Name": "Natural Wine Tasting"
    },
    {
        "Name": "Ornithology Club"
    },
    {
        "Name": "Public Speaking Practice"
    },
    {
        "Name": "Quantum Mechanics Study"
    },
    {
        "Name": "Reptile Keeping"
    },
    {
        "Name": "Scrapbooking Group"
    },
    {
        "Name": "Trail Running"
    },
    {
        "Name": "Urban Exploration"
    },
    {
        "Name": "Yoga Philosophy"
    },
    {
        "Name": "Zoo Volunteer Work"
    },
    {
        "Name": "Alternative Energy Discussion"
    },
    {
        "Name": "Breakdance Practice"
    },
    {
        "Name": "Comic Book Collecting"
    },
    {
        "Name": "Digital Art Workshop"
    },
    {
        "Name": "Emergency Preparedness"
    },
    {
        "Name": "Floral Design Class"
    },
    {
        "Name": "Guitar Pedal Building"
    },
    {
        "Name": "Hula Hooping"
    },
    {
        "Name": "Indoor Gardening"
    },
    {
        "Name": "Jeet Kune Do Practice"
    },
    {
        "Name": "Kinetic Sculpture Building"
    },
    {
        "Name": "Landscape Painting"
    },
    {
        "Name": "Marathon Training"
    },
    {
        "Name": "Nature Conservation Volunteering"
    },
    {
        "Name": "Opera Appreciation"
    },
    {
        "Name": "Permaculture Design"
    },
    {
        "Name": "Quantitative Finance"
    },
    {
        "Name": "Rock Painting"
    },
    {
        "Name": "Street Photography"
    },
    {
        "Name": "Tapas Cooking Class"
    },
    {
        "Name": "Urban Permaculture"
    },
    {
        "Name": "Vegan Lifestyle"
    },
    {
        "Name": "Whale Watching"
    },
    {
        "Name": "X-ray Astronomy Discussion"
    },
    {
        "Name": "Youth Leadership Development"
    },
    {
        "Name": "Zumba Fitness"
    },
    {
        "Name": "Animation Workshop"
    },
    {
        "Name": "Bharatanatyam Dance Practice"
    },
    {
        "Name": "Candle Making Class"
    },
    {
        "Name": "Drone Building"
    },
    {
        "Name": "Experimental Film Discussion"
    },
    {
        "Name": "Fencing Class"
    },
    {
        "Name": "Glass Etching"
    },
    {
        "Name": "Herbal Medicine Workshop"
    },
    {
        "Name": "Indigenous Art Appreciation"
    },
    {
        "Name": "Jogging Group"
    },
    {
        "Name": "Kombucha Brewing"
    },
    {
        "Name": "Laser Cutting Class"
    },
    {
        "Name": "Manga Drawing Class"
    },
    {
        "Name": "Natural Dyeing Workshop"
    },
    {
        "Name": "Outdoor Yoga Class"
    },
    {
        "Name": "Pottery Making"
    },
    {
        "Name": "Quantum Biology Discussion"
    },
    {
        "Name": "Rap Battle"
    },
    {
        "Name": "Screenprinting Workshop"
    },
    {
        "Name": "Thai Boxing Class"
    },
    {
        "Name": "Upcycling Clothing"
    },
    {
        "Name": "Vegetable Gardening"
    },
    {
        "Name": "Wild Foraging"
    },
    {
        "Name": "Xenobotany Discussion"
    },
    {
        "Name": "Youth Sports Coaching"
    },
    {
        "Name": "Zymurgy (Wine Making)"
    },
    {
        "Name": "Aromatherapy Class"
    },
    {
        "Name": "Brazilian Jiu-Jitsu Practice"
    },
    {
        "Name": "Cryptocurrency Investment"
    },
    {
        "Name": "Digital Photography"
    },
    {
        "Name": "Entrepreneurship Meetup"
    },
    {
        "Name": "French Conversation Practice"
    },
    {
        "Name": "Gastronomy Class"
    },
    {
        "Name": "Historical Role Play"
    },
    {
        "Name": "Indian Classical Music"
    },
    {
        "Name": "Jazz Dance Class"
    },
    {
        "Name": "Kite Flying"
    },
    {
        "Name": "Letterpress Printing"
    },
    {
        "Name": "Martial Arts Training"
    },
    {
        "Name": "Nature Photography"
    },
    {
        "Name": "Origami Workshop"
    },
    {
        "Name": "Podcast Creation"
    },
    {
        "Name": "Quantum Computing"
    },
    {
        "Name": "Renaissance Faire"
    },
    {
        "Name": "Tap Dance Class"
    },
    {
        "Name": "Virtual Reality Art"
    },
    {
        "Name": "Wine Appreciation"
    },
    {
        "Name": "Xylography (Wood Engraving)"
    },
    {
        "Name": "Acrobatic Dance"
    },
    {
        "Name": "Beach Volleyball"
    },
    {
        "Name": "Calligraphy Art"
    },
    {
        "Name": "Dog Training"
    },
    {
        "Name": "Entrepreneur Networking"
    },
    {
        "Name": "Flamenco Dancing"
    },
    {
        "Name": "Glassblowing"
    },
    {
        "Name": "Horror Movie Club"
    },
    {
        "Name": "Indoor Climbing"
    },
    {
        "Name": "Jewelry Making"
    },
    {
        "Name": "Kitesurfing"
    },
    {
        "Name": "Linguistics Study"
    },
    {
        "Name": "Murder Mystery Party"
    },
    {
        "Name": "Nature Documentary Watching"
    },
    {
        "Name": "Outdoor Cinema"
    },
    {
        "Name": "Plant-Based Cooking"
    },
    {
        "Name": "Quilting"
    },
    {
        "Name": "Science Fiction Book Club"
    },
    {
        "Name": "Tai Chi Class"
    },
    {
        "Name": "Vintage Clothes Shopping"
    },
    {
        "Name": "Wildlife Safari"
    },
    {
        "Name": "X-country Skiing"
    },
    {
        "Name": "Yodeling Class"
    },
    {
        "Name": "Zen Gardening"
    },
    {
        "Name": "Archery Class"
    },
    {
        "Name": "Basketball League"
    },
    {
        "Name": "Ceramic Painting"
    },
    {
        "Name": "Dream Interpretation"
    },
    {
        "Name": "Eco-friendly Lifestyle"
    },
    {
        "Name": "Fantasy Role-Play"
    },
    {
        "Name": "Graffiti Art Workshop"
    },
    {
        "Name": "Insect Collection"
    },
    {
        "Name": "Japanese Ikebana"
    },
    {
        "Name": "Knitting Club"
    },
    {
        "Name": "Latin Dance Class"
    },
    {
        "Name": "Mountain Biking"
    },
    {
        "Name": "Nature Survival Skills"
    },
    {
        "Name": "Organic Farming"
    },
    {
        "Name": "Puppetry"
    },
    {
        "Name": "Robotics Workshop"
    },
    {
        "Name": "Stand-Up Comedy"
    },
    {
        "Name": "Tango Dance Class"
    },
    {
        "Name": "Upholstery Workshop"
    },
    {
        "Name": "Vinyl Record Collecting"
    },
    {
        "Name": "Whittling"
    },
    {
        "Name": "Xylophone Class"
    },
    {
        "Name": "Youth Theater"
    },
    {
        "Name": "Zero-Waste Cooking"
    },
    {
        "Name": "Biological Research"
    },
    {
        "Name": "Choir Singing"
    },
    {
        "Name": "Diving Club"
    },
    {
        "Name": "Electronic Music Production"
    },
    {
        "Name": "Floral Art"
    },
    {
        "Name": "Gardening Workshop"
    },
    {
        "Name": "Homebrewing Beer"
    },
    {
        "Name": "Improvisation Theater"
    },
    {
        "Name": "Judo Class"
    },
    {
        "Name": "Kayaking Trip"
    },
    {
        "Name": "Life Drawing Class"
    },
    {
        "Name": "Neuroscience Study"
    },
    {
        "Name": "Oil Painting"
    },
    {
        "Name": "Photography Workshop"
    },
    {
        "Name": "Quasar Observation"
    },
    {
        "Name": "Robot Building"
    },
    {
        "Name": "Salsa Dancing"
    },
    {
        "Name": "Taiji Quan Practice"
    },
    {
        "Name": "Underwater Basket Weaving"
    },
    {
        "Name": "Volksmarching"
    },
    {
        "Name": "Water Polo Team"
    },
    {
        "Name": "Xing Yi Quan Practice"
    },
    {
        "Name": "Yachting"
    },
    {
        "Name": "Zoological Studies"
    },
    {
        "Name": "Amateur Radio Club"
    },
    {
        "Name": "Biology Laboratory Work"
    },
    {
        "Name": "Digital Illustration"
    },
    {
        "Name": "Environmental Activism"
    },
    {
        "Name": "Film Studies"
    },
    {
        "Name": "Geological Field Studies"
    },
    {
        "Name": "Hip Hop Dance Class"
    },
    {
        "Name": "Indoor Soccer Team"
    },
    {
        "Name": "Japanese Language Exchange"
    },
    {
        "Name": "Kung Fu Practice"
    },
    {
        "Name": "Literary Fiction Writing"
    },
    {
        "Name": "Mycology Studies"
    },
    {
        "Name": "Observational Astronomy"
    },
    {
        "Name": "Psychology Studies"
    },
    {
        "Name": "Renaissance Art Studies"
    },
    {
        "Name": "Street Dance Class"
    },
    {
        "Name": "Therapeutic Painting"
    },
    {
        "Name": "Vietnamese Language Exchange"
    },
    {
        "Name": "Woodworking Workshop"
    },
    {
        "Name": "X-ray Diffraction Studies"
    },
    {
        "Name": "Yoga Therapy"
    },
    {
        "Name": "Zen Buddhism Studies"
    },
    {
        "Name": "Astronomy Club"
    },
    {
        "Name": "Belly Dance Class"
    },
    {
        "Name": "Culinary Art"
    },
    {
        "Name": "DIY Projects"
    },
    {
        "Name": "Ethnography Study"
    },
    {
        "Name": "Fencing Club"
    },
    {
        "Name": "Guitar Class"
    },
    {
        "Name": "Historical Fiction Writing"
    },
    {
        "Name": "Jazz Club"
    },
    {
        "Name": "Mountain Hiking"
    },
    {
        "Name": "Numismatics (Coin Collecting)"
    },
    {
        "Name": "Russian Language Exchange"
    },
    {
        "Name": "Stand Up Paddleboarding"
    },
    {
        "Name": "Triathlon Training"
    },
    {
        "Name": "Volunteer Work"
    },
    {
        "Name": "Wilderness Survival Training"
    },
    {
        "Name": "Yoga Retreat"
    },
    {
        "Name": "Acoustic Music Club"
    },
    {
        "Name": "Cosplay Club"
    },
    {
        "Name": "Equestrian Sports"
    },
    {
        "Name": "Foraging"
    },
    {
        "Name": "Graphic Design Workshop"
    },
    {
        "Name": "Home Renovation Projects"
    },
    {
        "Name": "Investment Club"
    },
    {
        "Name": "Journalism Workshop"
    },
    {
        "Name": "Leatherworking"
    },
    {
        "Name": "Manga Drawing"
    },
    {
        "Name": "Nature Conservation"
    },
    {
        "Name": "Parkour"
    },
    {
        "Name": "Sustainability Workshop"
    },
    {
        "Name": "Thai Boxing"
    },
    {
        "Name": "Wood Carving"
    },
    {
        "Name": "X-Ray Astronomy"
    },
    {
        "Name": "Youth Leadership Training"
    },
    {
        "Name": "Zen Yoga"
    },
    {
        "Name": "Archaeology Field Work"
    },
    {
        "Name": "Baking Class"
    },
    {
        "Name": "Circus Skills Training"
    },
    {
        "Name": "Darts Team"
    },
    {
        "Name": "Ecology Field Work"
    },
    {
        "Name": "Figure Skating Class"
    },
    {
        "Name": "Geocaching"
    },
    {
        "Name": "Improv Comedy Class"
    },
    {
        "Name": "Juggling Class"
    },
    {
        "Name": "Knitting Circle"
    },
    {
        "Name": "Lacrosse Team"
    },
    {
        "Name": "Magic The Gathering Club"
    },
    {
        "Name": "Neurobiology Studies"
    },
    {
        "Name": "Ornithology Studies"
    },
    {
        "Name": "Paleontology Field Work"
    },
    {
        "Name": "Quasar Study Group"
    },
    {
        "Name": "Radio Controlled Car Racing"
    },
    {
        "Name": "Scuba Diving Club"
    },
    {
        "Name": "Taekwondo Class"
    },
    {
        "Name": "Underwater Hockey Team"
    },
    {
        "Name": "Veterinary Studies"
    },
    {
        "Name": "Weightlifting Team"
    },
    {
        "Name": "X-Ray Spectroscopy Study"
    },
    {
        "Name": "Yoga Teacher Training"
    },
    {
        "Name": "Zoology Field Work"
    },
    {
        "Name": "Astronomy Photography"
    },
    {
        "Name": "Bodybuilding Team"
    },
    {
        "Name": "Dog Training Class"
    },
    {
        "Name": "Environmental Studies"
    },
    {
        "Name": "Fantasy Football League"
    },
    {
        "Name": "Geology Field Work"
    },
    {
        "Name": "Homebrewing Club"
    },
    {
        "Name": "Ice Hockey Team"
    },
    {
        "Name": "Japanese Cooking Class"
    },
    {
        "Name": "Kickball Team"
    },
    {
        "Name": "Luthiery (Guitar Making)"
    },
    {
        "Name": "Meteorology Studies"
    },
    {
        "Name": "Nuclear Physics Study"
    },
    {
        "Name": "Quantum Computing Studies"
    },
    {
        "Name": "Rowing Team"
    },
    {
        "Name": "Stand-Up Paddleboarding Club"
    },
    {
        "Name": "Trombone Class"
    },
    {
        "Name": "Vietnamese Cooking Class"
    },
    {
        "Name": "Xenology Studies"
    },
    {
        "Name": "Youth Mentorship"
    },
    {
        "Name": "Zymurgy (Study of Brewing)"
    },
    {
        "Name": "Astronomy Discussion Group"
    },
    {
        "Name": "Bonsai Club"
    },
    {
        "Name": "Ceramic Art Class"
    },
    {
        "Name": "Data Science Club"
    },
    {
        "Name": "Fantasy Literature Club"
    },
    {
        "Name": "Gourmet Cooking Class"
    },
    {
        "Name": "Herpetology Studies"
    },
    {
        "Name": "Ice Sculpting Class"
    },
    {
        "Name": "Kabbalah Studies"
    },
    {
        "Name": "Linguistics Studies"
    },
    {
        "Name": "Nautical Archaeology Studies"
    },
    {
        "Name": "Outdoor Survival Skills Training"
    },
    {
        "Name": "Paranormal Studies Group"
    },
    {
        "Name": "Quantum Field Theory Studies"
    },
    {
        "Name": "Rock Collecting Club"
    },
    {
        "Name": "Scuba Diving Class"
    },
    {
        "Name": "Theoretical Physics Studies"
    },
    {
        "Name": "Underwater Photography Class"
    },
    {
        "Name": "Volcanology Field Studies"
    },
    {
        "Name": "Whittling Class"
    },
    {
        "Name": "Xeriscaping Workshop"
    },
    {
        "Name": "Yoga Philosophy Studies"
    },
    {
        "Name": "Zymurgy Club"
    },
    {
        "Name": "Amateur Astronomy Club"
    },
    {
        "Name": "Bharatanatyam Dance Class"
    },
    {
        "Name": "Cybersecurity Club"
    },
    {
        "Name": "Djembe Drumming Class"
    },
    {
        "Name": "Ecotourism Club"
    },
    {
        "Name": "Flamenco Dance Class"
    },
    {
        "Name": "Gastronomy Club"
    },
    {
        "Name": "Horology (Watch Making) Class"
    },
    {
        "Name": "Italian Cinema Club"
    },
    {
        "Name": "Japanese Tea Ceremony Class"
    },
    {
        "Name": "Kirtan Singing Class"
    },
    {
        "Name": "Lacemaking Class"
    },
    {
        "Name": "Medieval History Studies"
    },
    {
        "Name": "Numerology Studies"
    },
    {
        "Name": "Opera Singing Class"
    },
    {
        "Name": "Paragliding Club"
    },
    {
        "Name": "Quilling (Paper Filigree) Class"
    },
    {
        "Name": "Space Science Studies"
    },
    {
        "Name": "Urban Sketching Club"
    },
    {
        "Name": "Vexillology (Study of Flags) Club"
    },
    {
        "Name": "Weaving Class"
    },
    {
        "Name": "Xenoculture Studies"
    },
    {
        "Name": "Yacht Racing Team"
    },
    {
        "Name": "Zoography Studies"
    },
    {
        "Name": "Acoustic Guitar Lessons"
    },
    {
        "Name": "Ballet Class"
    },
    {
        "Name": "Carpentry Workshop"
    },
    {
        "Name": "Drone Photography Class"
    },
    {
        "Name": "Embroidery Club"
    },
    {
        "Name": "French Literature Club"
    },
    {
        "Name": "Geography Study Group"
    },
    {
        "Name": "Hiking Club"
    },
    {
        "Name": "Indian Classical Music Lessons"
    },
    {
        "Name": "Judo Club"
    },
    {
        "Name": "Karate Class"
    },
    {
        "Name": "Music Theory Lessons"
    },
    {
        "Name": "Nutrition Workshop"
    },
    {
        "Name": "Orchestra Group"
    },
    {
        "Name": "Pottery Class"
    },
    {
        "Name": "Salsa Dance Class"
    },
    {
        "Name": "Tennis Club"
    },
    {
        "Name": "Urban Gardening Club"
    },
    {
        "Name": "Violin Lessons"
    },
    {
        "Name": "Xiangqi (Chinese Chess) Club"
    },
    {
        "Name": "Zither Lessons"
    },
    {
        "Name": "Board Game Club"
    },
    {
        "Name": "Classical Guitar Lessons"
    },
    {
        "Name": "Dungeons and Dragons Club"
    },
    {
        "Name": "Egyptology Study Group"
    },
    {
        "Name": "Glassblowing Class"
    },
    {
        "Name": "Harmonica Lessons"
    },
    {
        "Name": "Improv Theatre Class"
    },
    {
        "Name": "Japanese Calligraphy Class"
    },
    {
        "Name": "Kickboxing Club"
    },
    {
        "Name": "Lacrosse Club"
    },
    {
        "Name": "Marathon Training Group"
    },
    {
        "Name": "Numismatics (Coin Collecting) Club"
    },
    {
        "Name": "Portrait Painting Class"
    },
    {
        "Name": "Quilting Workshop"
    },
    {
        "Name": "Swing Dance Class"
    },
    {
        "Name": "Underwater Basket Weaving Class"
    },
    {
        "Name": "Vegan Cooking Class"
    },
    {
        "Name": "Weightlifting Club"
    },
    {
        "Name": "Xylophone Lessons"
    },
    {
        "Name": "Youth Theatre Group"
    },
    {
        "Name": "Zen Buddhism Study Group"
    },
    {
        "Name": "Book Writing Group"
    },
    {
        "Name": "Classical Music Appreciation Group"
    },
    {
        "Name": "Digital Painting Class"
    },
    {
        "Name": "Entrepreneurship Network"
    },
    {
        "Name": "Figure Drawing Workshop"
    },
    {
        "Name": "Golfing Buddies"
    },
    {
        "Name": "Handwriting Analysis Study Group"
    },
    {
        "Name": "Italian Cooking Class"
    },
    {
        "Name": "Japanese Language Study Group"
    },
    {
        "Name": "Leather Crafting Workshop"
    },
    {
        "Name": "Movie Discussion Group"
    },
    {
        "Name": "Nature Photography Class"
    },
    {
        "Name": "Opera Appreciation Club"
    },
    {
        "Name": "Potluck Dinner Group"
    },
    {
        "Name": "Quantum Mechanics Study Group"
    },
    {
        "Name": "Rock Climbing Club"
    },
    {
        "Name": "Sushi Making Class"
    },
    {
        "Name": "Travel Buddies Network"
    },
    {
        "Name": "Vegetarian Cooking Class"
    },
    {
        "Name": "Xenobiology Discussion Group"
    },
    {
        "Name": "Yoga Meditation Group"
    },
    {
        "Name": "Zumba Fitness Class"
    },
    {
        "Name": "Anime Discussion Group"
    },
    {
        "Name": "Beach Volleyball Team"
    },
    {
        "Name": "Chess Club"
    },
    {
        "Name": "Drama Acting Workshop"
    },
    {
        "Name": "Ethnic Cooking Class"
    },
    {
        "Name": "Fashion Design Workshop"
    },
    {
        "Name": "History Book Club"
    },
    {
        "Name": "Improv Comedy Group"
    },
    {
        "Name": "Jazz Band"
    },
    {
        "Name": "Novel Writing Group"
    },
    {
        "Name": "Outdoor Adventure Club"
    },
    {
        "Name": "Philosophy Discussion Group"
    },
    {
        "Name": "Rock Music Band"
    },
    {
        "Name": "Scrapbooking Workshop"
    },
    {
        "Name": "Triathlon Training Group"
    },
    {
        "Name": "Urban Exploration Group"
    },
    {
        "Name": "Vegan Lifestyle Network"
    },
    {
        "Name": "Wine Tasting Club"
    },
    {
        "Name": "Xerography Art Class"
    },
    {
        "Name": "Yoga Instructor Training"
    },
    {
        "Name": "Zoology Discussion Group"
    },
    {
        "Name": "Astrophotography Group"
    },
    {
        "Name": "Breakdancing Class"
    },
    {
        "Name": "Crochet Club"
    },
    {
        "Name": "Digital Marketing Workshop"
    },
    {
        "Name": "Freelance Writers Network"
    },
    {
        "Name": "Glass Painting Class"
    },
    {
        "Name": "Horse Riding Club"
    },
    {
        "Name": "Ice Skating Club"
    },
    {
        "Name": "Kickboxing Workshop"
    },
    {
        "Name": "Latin Language Study Group"
    },
    {
        "Name": "Motorbike Club"
    },
    {
        "Name": "Nature Sketching Group"
    },
    {
        "Name": "Outdoor Fitness Group"
    },
    {
        "Name": "Poetry Writing Workshop"
    },
    {
        "Name": "Quiz Club"
    },
    {
        "Name": "Rowing Club"
    },
    {
        "Name": "Taekwondo Club"
    },
    {
        "Name": "Urban Sketching Group"
    },
    {
        "Name": "Volleyball Team"
    },
    {
        "Name": "Watercolor Painting Class"
    },
    {
        "Name": "X-country Skiing Club"
    },
    {
        "Name": "Zine Making Workshop"
    },
    {
        "Name": "Bird Watching Group"
    },
    {
        "Name": "Calligraphy Class"
    },
    {
        "Name": "DJ Workshop"
    },
    {
        "Name": "Euchre Card Game Club"
    },
    {
        "Name": "Gymnastics Club"
    },
    {
        "Name": "Harmonica Workshop"
    },
    {
        "Name": "Indoor Rock Climbing Group"
    },
    {
        "Name": "Kite Surfing Group"
    },
    {
        "Name": "Linguistics Discussion Group"
    },
    {
        "Name": "Mountain Biking Club"
    },
    {
        "Name": "Novel Reading Group"
    },
    {
        "Name": "Orienteering Club"
    },
    {
        "Name": "Philately (Stamp Collecting) Club"
    },
    {
        "Name": "Quidditch Club"
    },
    {
        "Name": "Renaissance Art Study Group"
    },
    {
        "Name": "Sewing Workshop"
    },
    {
        "Name": "Taiko Drumming Workshop"
    },
    {
        "Name": "Underwater Hockey Club"
    },
    {
        "Name": "Ventriloquism Workshop"
    },
    {
        "Name": "Windsurfing Club"
    },
    {
        "Name": "X-treme Sports Club"
    },
    {
        "Name": "Yarn Bombing Group"
    },
    {
        "Name": "Zymurgy (Home Brewing) Club"
    }
]